treemirror/__init__.py
treemirror/treemirror.py
treemirror-0.1.1.dist-info/LICENSE
treemirror-0.1.1.dist-info/METADATA
treemirror-0.1.1.dist-info/WHEEL
treemirror-0.1.1.dist-info/entry_points.txt
treemirror-0.1.1.dist-info/RECORD
