Metadata-Version: 2.1
Name: treemirror
Version: 0.1.1
Summary: A program to mirror the directory structure of a source directory to a destination directory.
License: MIT
Author: Samyak Jain
Author-email: samyak.jn11@gmail.com
Requires-Python: >=3.11,<4.0
Classifier: License :: OSI Approved :: MIT License
Classifier: Programming Language :: Python :: 3
Classifier: Programming Language :: Python :: 3.11
Requires-Dist: argparse (>=1.4.0,<2.0.0)
Requires-Dist: shutil-extra (>=0.0.6,<0.0.7)
Requires-Dist: tqdm (>=4.65.0,<5.0.0)
